taburu/__init__.py
taburu/aggregate.py
taburu/channel.py
taburu/command.py
taburu/event.py
taburu/state.py
taburu/table.py
taburu-2020.5.9.dist-info/LICENSE
taburu-2020.5.9.dist-info/METADATA
taburu-2020.5.9.dist-info/WHEEL
taburu-2020.5.9.dist-info/top_level.txt
taburu-2020.5.9.dist-info/RECORD
