Metadata-Version: 2.1
Name: taburu
Version: 2020.5.9
Summary: a module that supports an event-sourced system of tracking parameterizations of methods.
Home-page: https://github.com/TRI-AMDD/taburu
Author: joseph.montoya
Author-email: joseph.montoya@tri.global
Maintainer: joseph.montoya
Maintainer-email: joseph.montoya@tri.global
License: Apache
Platform: UNKNOWN
Classifier: Programming Language :: Python :: 3
Classifier: License :: OSI Approved :: Apache Software License
Classifier: Operating System :: OS Independent
Requires-Dist: monty (>=3.0.2)
Requires-Dist: indexed (==1.0.0)
Requires-Dist: tqdm (>=4.46.0)
